django_slow_log
