Metadata-Version: 1.0
Name: django-slow-log
Version: 0.1.3
Summary: slow request log for django
Home-page: http://github.com/jmoiron/django-slow-log
Author: Jason Moiron
Author-email: jmoiron@jmoiron.net
License: MIT
Keywords: django profiling slow request
Platform: UNKNOWN
Classifier: Development Status :: 4 - Beta
Classifier: Framework :: Django
Classifier: Topic :: Internet :: WWW/HTTP
Classifier: Topic :: Internet :: Log Analysis
Classifier: License :: OSI Approved :: MIT License
Classifier: Intended Audience :: Developers
Classifier: Operating System :: POSIX
